unveil/__init__.py
unveil/__main__.py
unveil/core.py
unveil_python-0.3.0.dist-info/licenses/LICENSE
unveil_python-0.3.0.dist-info/METADATA
unveil_python-0.3.0.dist-info/WHEEL
unveil_python-0.3.0.dist-info/top_level.txt
unveil_python-0.3.0.dist-info/RECORD
