Metadata-Version: 2.4
Name: unveil-python
Version: 0.3.0
Summary: Implementation of UNVEIL
Author-email: Nicolas Delinte <nicolas.delinte@uclouvain.be>
License-Expression: GPL-3.0-only
Project-URL: GitHub, https://github.com/DelinteNicolas/UNVEIL
Keywords: tractography,viewer
Classifier: Intended Audience :: Science/Research
Classifier: Natural Language :: English
Classifier: Programming Language :: Python
License-File: LICENSE
Requires-Dist: dipy
Requires-Dist: pyvista
Requires-Dist: pyvistaqt
Requires-Dist: PyQt6
Dynamic: license-file
